duke_typem/__init__.py
duke_typem/cli.py
duke_typem/data_models/__init__.py
duke_typem/data_models/configuration.py
duke_typem/data_models/logger.py
DukeTypem2D-0.3.2.dist-info/LICENSE
DukeTypem2D-0.3.2.dist-info/METADATA
DukeTypem2D-0.3.2.dist-info/WHEEL
DukeTypem2D-0.3.2.dist-info/entry_points.txt
DukeTypem2D-0.3.2.dist-info/top_level.txt
DukeTypem2D-0.3.2.dist-info/zip-safe
DukeTypem2D-0.3.2.dist-info/RECORD
