Metadata-Version: 2.1
Name: DukeTypem2D
Version: 0.3.2
Summary: Improve readability, spelling and expression of your text documents
Author: Torben Menke
Author-email: Ingmar Splitt <ingmar.splitt@tu-dresden.de>
Maintainer-email: Ingmar Splitt <ingmar.splitt@tu-dresden.de>
License: GNU GENERAL PUBLIC LICENSE
Project-URL: homepage, https://pypi.org/project/duketypem2d/
Project-URL: documentation, https://pypi.org/project/duketypem2d/
Project-URL: repository, https://github.com/orgua/DukeTypem2D
Keywords: spelling,latex,readability,typos,misspelling,expression,phrasing,diction
Platform: unix
Platform: linux
Platform: osx
Platform: cygwin
Platform: win32
Platform: win64
Classifier: Intended Audience :: Science/Research
Classifier: Programming Language :: Python :: 3
Classifier: Operating System :: OS Independent
Classifier: Natural Language :: English
Classifier: Development Status :: 3 - Alpha
Requires-Python: >=3.7
License-File: LICENSE
Requires-Dist: click
Requires-Dist: pydantic
Requires-Dist: PyYAML
Requires-Dist: toml
Provides-Extra: dev
Requires-Dist: build ; extra == 'dev'
Requires-Dist: twine ; extra == 'dev'
Requires-Dist: black ; extra == 'dev'
Requires-Dist: pylint ; extra == 'dev'
Requires-Dist: flake8 ; extra == 'dev'
Requires-Dist: pyright ; extra == 'dev'
Requires-Dist: pre-commit ; extra == 'dev'
Requires-Dist: ruff ; extra == 'dev'
Requires-Dist: tomli ; extra == 'dev'
Provides-Extra: test
Requires-Dist: pytest ; extra == 'test'
Requires-Dist: pytest-cov ; extra == 'test'
Requires-Dist: pytest-click ; extra == 'test'
Requires-Dist: coverage ; extra == 'test'
Provides-Extra: web
Requires-Dist: fastapi ; extra == 'web'
